lsdc/__init__.py
lsdc-0.0.0.dist-info/METADATA
lsdc-0.0.0.dist-info/WHEEL
lsdc-0.0.0.dist-info/top_level.txt
lsdc-0.0.0.dist-info/RECORD
