Metadata-Version: 2.4
Name: lsdc
Version: 0.0.0
Summary: Logical Syndrome Dependent Characterization.
Author-email: Matt Girling <me@mattgirling.com>
